<?xml version="1.0" encoding="UTF-8"?>
<modsCollection xmlns="http://www.loc.gov/mods/v3">
<mods ID="S.Amjath-Babu-etal-2019-Integrated">
    <titleInfo>
        <title>Integrated modelling of the impacts of hydropower projects on the water-food-energy nexus in a transboundary Himalayan river basin</title>
    </titleInfo>
    <name type="personal">
        <namePart type="given">T</namePart>
        <namePart type="family">S. Amjath-Babu</namePart>
        <role>
            <roleTerm authority="marcrelator" type="text">author</roleTerm>
        </role>
    </name>
    <name type="personal">
        <namePart type="given">B</namePart>
        <namePart type="family">Sharma</namePart>
        <role>
            <roleTerm authority="marcrelator" type="text">author</roleTerm>
        </role>
    </name>
    <name type="personal">
        <namePart type="given">R</namePart>
        <namePart type="family">Brouwer</namePart>
        <role>
            <roleTerm authority="marcrelator" type="text">author</roleTerm>
        </role>
    </name>
    <name type="personal">
        <namePart type="given">G</namePart>
        <namePart type="family">Rasul</namePart>
        <role>
            <roleTerm authority="marcrelator" type="text">author</roleTerm>
        </role>
    </name>
    <name type="personal">
        <namePart type="given">S</namePart>
        <namePart type="family">Wahid</namePart>
        <role>
            <roleTerm authority="marcrelator" type="text">author</roleTerm>
        </role>
    </name>
    <name type="personal">
        <namePart type="given">Nilhari</namePart>
        <namePart type="family">Neupane</namePart>
        <role>
            <roleTerm authority="marcrelator" type="text">author</roleTerm>
        </role>
    </name>
    <name type="personal">
        <namePart type="given">U</namePart>
        <namePart type="family">Bhattarai</namePart>
        <role>
            <roleTerm authority="marcrelator" type="text">author</roleTerm>
        </role>
    </name>
    <name type="personal">
        <namePart type="given">S</namePart>
        <namePart type="family">Sieber</namePart>
        <role>
            <roleTerm authority="marcrelator" type="text">author</roleTerm>
        </role>
    </name>
    <originInfo>
        <dateIssued>2019</dateIssued>
    </originInfo>
    <typeOfResource>text</typeOfResource>
    <relatedItem type="host">
        <titleInfo>
            <title>Global Water Futures 2019</title>
        </titleInfo>
        <originInfo>
            <publisher>University of Waterloo</publisher>
            <place>
                <placeTerm type="text">Online</placeTerm>
            </place>
        </originInfo>
        <genre authority="marcgt">conference publication</genre>
    </relatedItem>
    <identifier type="citekey">S. Amjath-Babu-etal-2019-Integrated</identifier>
    <identifier type="doi">10.1016/J.APENERGY.2019.01.147</identifier>
    <location>
        <url>https://aclanthology.org/2019.GWF-1.26</url>
    </location>
    <part>
        <date>2019</date>
    </part>
</mods>
</modsCollection>
